bareasgi_compression/__init__.py
bareasgi_compression/__version__.py
bareasgi_compression/middleware.py
bareasgi_compression-2.0.1.dist-info/LICENSE
bareasgi_compression-2.0.1.dist-info/METADATA
bareasgi_compression-2.0.1.dist-info/WHEEL
bareasgi_compression-2.0.1.dist-info/top_level.txt
bareasgi_compression-2.0.1.dist-info/RECORD
